setup.py
testml/__init__.py
testml/bridge.py
testml/stdlib.py
testml/util.py
testml.egg-info/PKG-INFO
testml.egg-info/SOURCES.txt
testml.egg-info/dependency_links.txt
testml.egg-info/requires.txt
testml.egg-info/top_level.txt
testml/run/__init__.py
testml/run/tap.py
testml/run/unit.py