Metadata-Version: 2.1
Name: testml
Version: 0.0.1
Summary: TestML framework for Python
Home-page: https://testml.org
Author: Ingy döt Net
Author-email: ingy@ingy.net
License: MIT
Project-URL: Source, https://github.com/testml-lang/testml/
Project-URL: Bug Reports, https://github.com/testml-lang/testml/issues/
Keywords: test testing development
Platform: UNKNOWN
Classifier: Development Status :: 3 - Alpha
Classifier: Intended Audience :: Developers
Classifier: Topic :: Software Development :: Testing
Classifier: License :: OSI Approved :: MIT License
Classifier: Programming Language :: Python :: 2
Classifier: Programming Language :: Python :: 2.7
Provides-Extra: test
Provides-Extra: dev
